Workbook

Sheet Checklist
A1: GCSE curriculum coverage checklist
A2: Choose ☐ or ☑ in the Complete column. Filter by subject, level, paper or tier to plan revision.
A3: Complete | B3: Subject | C3: Level 1 | D3: Level 2 | E3: Level 3 | F3: Description | G3: Component / paper | H3: Tier | I3: Applicability | J3: Source
A4: ☐ | B4: Business | C4: Theme 1: Investigating small business | D4: 1.1 Enterprise and entrepreneurship | E4: Added value and the role and characteristics of entrepreneurs | G4: Paper 1 | H4: All tiers | I4: Common | J4: Open source
A5: ☐ | B5: Business | C5: Theme 1: Investigating small business | D5: 1.1 Enterprise and entrepreneurship | E5: Customer needs | G5: Paper 1 | H5: All tiers | I5: Common | J5: Open source
A6: ☐ | B6: Business | C6: Theme 1: Investigating small business | D6: 1.1 Enterprise and entrepreneurship | E6: Dynamic business ideas and obsolescence | G6: Paper 1 | H6: All tiers | I6: Common | J6: Open source
A7: ☐ | B7: Business | C7: Theme 1: Investigating small business | D7: 1.1 Enterprise and entrepreneurship | E7: Enterprise | G7: Paper 1 | H7: All tiers | I7: Common | J7: Open source
A8: ☐ | B8: Business | C8: Theme 1: Investigating small business | D8: 1.1 Enterprise and entrepreneurship | E8: Risk and reward | G8: Paper 1 | H8: All tiers | I8: Common | J8: Open source
A9: ☐ | B9: Business | C9: Theme 1: Investigating small business | D9: 1.2 Spotting a business opportunity | E9: Customer needs | G9: Paper 1 | H9: All tiers | I9: Common | J9: Open source
A10: ☐ | B10: Business | C10: Theme 1: Investigating small business | D10: 1.2 Spotting a business opportunity | E10: Market mapping and competition | G10: Paper 1 | H10: All tiers | I10: Common | J10: Open source
A11: ☐ | B11: Business | C11: Theme 1: Investigating small business | D11: 1.2 Spotting a business opportunity | E11: Primary and secondary market research | G11: Paper 1 | H11: All tiers | I11: Common | J11: Open source
A12: ☐ | B12: Business | C12: Theme 1: Investigating small business | D12: 1.2 Spotting a business opportunity | E12: Qualitative and quantitative data and reliability | G12: Paper 1 | H12: All tiers | I12: Common | J12: Open source
A13: ☐ | B13: Business | C13: Theme 1: Investigating small business | D13: 1.2 Spotting a business opportunity | E13: Segmentation | G13: Paper 1 | H13: All tiers | I13: Common | J13: Open source
A14: ☐ | B14: Business | C14: Theme 1: Investigating small business | D14: 1.3 Putting a business idea into practice | E14: Appropriate sources of finance | G14: Paper 1 | H14: All tiers | I14: Common | J14: Open source
A15: ☐ | B15: Business | C15: Theme 1: Investigating small business | D15: 1.3 Putting a business idea into practice | E15: Break-even and margin of safety | G15: Paper 1 | H15: All tiers | I15: Common | J15: Open source
... A62: ☐ | B62: Business | C62: Theme 2: Building a business | D62: 2.5 Making human resource decisions | E62: Recruitment and training | G62: Paper 2 | H62: All tiers | I62: Common | J62: Open source
A63: ☐ | B63: Combined Science | C63: Atomic structure | D63: Atomic models | G63: Physics Paper 1 | H63: All tiers | I63: Common | J63: Open source
A64: ☐ | B64: Combined Science | C64: Atomic structure | D64: Half-life and contamination | G64: Physics Paper 1 | H64: All tiers | I64: Common | J64: Open source
A65: ☐ | B65: Combined Science | C65: Atomic structure | D65: Isotopes and nuclear radiation | G65: Physics Paper 1 | H65: All tiers | I65: Common | J65: Open source
A66: ☐ | B66: Combined Science | C66: Atomic structure | D66: Uses and hazards of radiation | G66: Physics Paper 1 | H66: All tiers | I66: Common | J66: Open source
A67: ☐ | B67: Combined Science | C67: Atomic structure and the periodic table | D67: 1 and 7 | G67: Chemistry Paper 1 | H67: All tiers | I67: Common | J67: Open source
A68: ☐ | B68: Combined Science | C68: Atomic structure and the periodic table | D68: Atomic models and electronic structure | G68: Chemistry Paper 1 | H68: All tiers | I68: Common | J68: Open source
A69: ☐ | B69: Combined Science | C69: Atomic structure and the periodic table | D69: Atoms | G69: Chemistry Paper 1 | H69: All tiers | I69: Common | J69: Open source
A70: ☐ | B70: Combined Science | C70: Atomic structure and the periodic table | D70: Elements | G70: Chemistry Paper 1 | H70: All tiers | I70: Common | J70: Open source
A71: ☐ | B71: Combined Science | C71: Atomic structure and the periodic table | D71: Groups 0 | G71: Chemistry Paper 1 | H71: All tiers | I71: Common | J71: Open source
A72: ☐ | B72: Combined Science | C72: Atomic structure and the periodic table | D72: Mixtures and equations | G72: Chemistry Paper 1 | H72: All tiers | I72: Common | J72: Open source
A73: ☐ | B73: Combined Science | C73: Atomic structure and the periodic table | D73: Periodic table development | G73: Chemistry Paper 1 | H73: All tiers | I73: Common | J73: Open source
A74: ☐ | B74: Combined Science | C74: Atomic structure and the periodic table | D74: Transition metals | G74: Chemistry Paper 1 | H74: All tiers | I74: Common | J74: Open source
... A204: ☐ | B204: Combined Science | C204: Waves | D204: Wave properties and equations | G204: Physics Paper 2 | H204: All tiers | I204: Common | J204: Open source
A205: ☐ | B205: Design and Technology | C205: Core technical principles | D205: Developments in new materials | E205: Composite and technical textiles | G205: Paper 1 Section A | H205: All tiers | I205: Common | J205: Open source
A206: ☐ | B206: Design and Technology | C206: Core technical principles | D206: Developments in new materials | E206: Cost and sustainability | G206: Paper 1 Section A | H206: All tiers | I206: Common | J206: Open source
A207: ☐ | B207: Design and Technology | C207: Core technical principles | D207: Developments in new materials | E207: Evaluating functional benefit | G207: Paper 1 Section A | H207: All tiers | I207: Common | J207: Open source
A208: ☐ | B208: Design and Technology | C208: Core technical principles | D208: Developments in new materials | E208: Modern | G208: Paper 1 Section A | H208: All tiers | I208: Common | J208: Open source
A209: ☐ | B209: Design and Technology | C209: Core technical principles | D209: Developments in new materials | E209: Properties and applications | G209: Paper 1 Section A | H209: All tiers | I209: Common | J209: Open source
A210: ☐ | B210: Design and Technology | C210: Core technical principles | D210: Developments in new materials | E210: Smart | G210: Paper 1 Section A | H210: All tiers | I210: Common | J210: Open source
A211: ☐ | B211: Design and Technology | C211: Core technical principles | D211: Energy generation and storage | E211: Arguments for and against sources | G211: Paper 1 Section A | H211: All tiers | I211: Common | J211: Open source
A212: ☐ | B212: Design and Technology | C212: Core technical principles | D212: Energy generation and storage | E212: Batteries | G212: Paper 1 Section A | H212: All tiers | I212: Common | J212: Open source
A213: ☐ | B213: Design and Technology | C213: Core technical principles | D213: Energy generation and storage | E213: Fossil fuels | G213: Paper 1 Section A | H213: All tiers | I213: Common | J213: Open source
A214: ☐ | B214: Design and Technology | C214: Core technical principles | D214: Energy generation and storage | E214: Kinetic storage and energy-system selection | G214: Paper 1 Section A | H214: All tiers | I214: Common | J214: Open source
A215: ☐ | B215: Design and Technology | C215: Core technical principles | D215: Energy generation and storage | E215: Nuclear and renewable generation | G215: Paper 1 Section A | H215: All tiers | I215: Common | J215: Open source
A216: ☐ | B216: Design and Technology | C216: Core technical principles | D216: Materials and working properties | E216: Categories and common types of papers and boards | G216: Paper 1 Section A | H216: All tiers | I216: Common | J216: Open source
... A317: ☐ | B317: English Language | C317: Creative reading | D317: Analysing structure | E317: Sequence | G317: Paper 1 Section A | H317: All tiers | I317: Common | J317: Open source
A318: ☐ | B318: English Language | C318: Creative reading | D318: Evaluating a text | F318: Judge a statement about the text using precise evidence and analysis of methods. | G318: Paper 1 Section A | H318: All tiers | I318: Common | J318: Open source
A319: ☐ | B319: English Language | C319: Creative reading | D319: Selecting explicit information | F319: Select four relevant details from a specified part of the source. | G319: Paper 1 Section A | H319: All tiers | I319: Common | J319: Open source
A320: ☐ | B320: English Language | C320: Creative writing | F320: Write an effective description or narrative with deliberate organisation and accurate technical control. | G320: Paper 1 Section B | H320: All tiers | I320: Common | J320: Open source
A321: ☐ | B321: English Language | C321: Spoken Language | D321: Present information and ideas | G321: Spoken Language endorsement | H321: All tiers | I321: Common | J321: Open source
A322: ☐ | B322: English Language | C322: Spoken Language | D322: Respond to questions and use spoken Standard English | G322: Spoken Language endorsement | H322: All tiers | I322: Common | J322: Open source
A323: ☐ | B323: English Language | C323: Writers viewpoints and perspectives | D323: Analysing non-fiction language | F323: Explain how a writer uses language to present a viewpoint or experience. | G323: Paper 2 Section A | H323: All tiers | I323: Common | J323: Open source
A324: ☐ | B324: English Language | C324: Writers viewpoints and perspectives | D324: Comparing viewpoints and methods | F324: Compare perspectives and how the writers convey them across both sources. | G324: Paper 2 Section A | H324: All tiers | I324: Common | J324: Open source
A325: ☐ | B325: English Language | C325: Writers viewpoints and perspectives | D325: Identifying true statements | F325: Select four true statements from a specified part of a source. | G325: Paper 2 Section A | H325: All tiers | I325: Common | J325: Open source
A326: ☐ | B326: English Language | C326: Writers viewpoints and perspectives | D326: Synthesising differences | F326: Infer and summarise differences or similarities across two sources. | G326: Paper 2 Section A | H326: All tiers | I326: Common | J326: Open source
A327: ☐ | B327: English Language | C327: Writing a viewpoint | D327: Purpose and form | G327: Paper 2 Section B | H327: All tiers | I327: Common | J327: Open source
A328: ☐ | B328: English Language | C328: Writing a viewpoint | D328: Write a coherent argument or viewpoint for a specified audience | G328: Paper 2 Section B | H328: All tiers | I328: Common | J328: Open source
A329: ☐ | B329: English Literature | C329: A Christmas Carol | D329: A Christmas Carol: characters | E329: Fezziwig and Belle | G329: Paper 1 Section B | H329: All tiers | I329: Common | J329: Open source
A330: ☐ | B330: English Literature | C330: A Christmas Carol | D330: A Christmas Carol: characters | E330: Fred | G330: Paper 1 Section B | H330: All tiers | I330: Common | J330: Open source
A331: ☐ | B331: English Literature | C331: A Christmas Carol | D331: A Christmas Carol: characters | E331: Marley | G331: Paper 1 Section B | H331: All tiers | I331: Common | J331: Open source
A332: ☐ | B332: English Literature | C332: A Christmas Carol | D332: A Christmas Carol: characters | E332: Scrooge | G332: Paper 1 Section B | H332: All tiers | I332: Common | J332: Open source
A333: ☐ | B333: English Literature | C333: A Christmas Carol | D333: A Christmas Carol: characters | E333: The Cratchits | G333: Paper 1 Section B | H333: All tiers | I333: Common | J333: Open source
A334: ☐ | B334: English Literature | C334: A Christmas Carol | D334: A Christmas Carol: characters | E334: The three Ghosts | G334: Paper 1 Section B | H334: All tiers | I334: Common | J334: Open source
A335: ☐ | B335: English Literature | C335: A Christmas Carol | D335: A Christmas Carol: language, form and structure | E335: Analyse symbolism | G335: Paper 1 Section B | H335: All tiers | I335: Common | J335: Open source
A336: ☐ | B336: English Literature | C336: A Christmas Carol | D336: A Christmas Carol: language, form and structure | E336: Contrasts | G336: Paper 1 Section B | H336: All tiers | I336: Common | J336: Open source
A337: ☐ | B337: English Literature | C337: A Christmas Carol | D337: A Christmas Carol: language, form and structure | E337: Narrative voice | G337: Paper 1 Section B | H337: All tiers | I337: Common | J337: Open source
A338: ☐ | B338: English Literature | C338: A Christmas Carol | D338: A Christmas Carol: language, form and structure | E338: Setting | G338: Paper 1 Section B | H338: All tiers | I338: Common | J338: Open source
A339: ☐ | B339: English Literature | C339: A Christmas Carol | D339: A Christmas Carol: language, form and structure | E339: Supernatural elements and the novella form | G339: Paper 1 Section B | H339: All tiers | I339: Common | J339: Open source
A340: ☐ | B340: English Literature | C340: A Christmas Carol | D340: A Christmas Carol: plot and structure | F340: Track Scrooge through the five staves and explain the purpose of his transformation. | G340: Paper 1 Section B | H340: All tiers | I340: Common | J340: Open source
A341: ☐ | B341: English Literature | C341: A Christmas Carol | D341: A Christmas Carol: themes and context | E341: Christmas | G341: Paper 1 Section B | H341: All tiers | I341: Common | J341: Open source
A342: ☐ | B342: English Literature | C342: A Christmas Carol | D342: A Christmas Carol: themes and context | E342: Education and Victorian context | G342: Paper 1 Section B | H342: All tiers | I342: Common | J342: Open source
A343: ☐ | B343: English Literature | C343: A Christmas Carol | D343: A Christmas Carol: themes and context | E343: Family | G343: Paper 1 Section B | H343: All tiers | I343: Common | J343: Open source
A344: ☐ | B344: English Literature | C344: A Christmas Carol | D344: A Christmas Carol: themes and context | E344: Poverty | G344: Paper 1 Section B | H344: All tiers | I344: Common | J344: Open source
A345: ☐ | B345: English Literature | C345: A Christmas Carol | D345: A Christmas Carol: themes and context | E345: Redemption | G345: Paper 1 Section B | H345: All tiers | I345: Common | J345: Open source
A346: ☐ | B346: English Literature | C346: A Christmas Carol | D346: A Christmas Carol: themes and context | E346: Social responsibility | G346: Paper 1 Section B | H346: All tiers | I346: Common | J346: Open source
A347: ☐ | B347: English Literature | C347: An Inspector Calls | D347: An Inspector Calls: characters | E347: Arthur and Sybil Birling | G347: Paper 2 Section A | H347: All tiers | I347: Common | J347: Open source
A348: ☐ | B348: English Literature | C348: An Inspector Calls | D348: An Inspector Calls: characters | E348: Eric | G348: Paper 2 Section A | H348: All tiers | I348: Common | J348: Open source
A349: ☐ | B349: English Literature | C349: An Inspector Calls | D349: An Inspector Calls: characters | E349: Gerald and Eva Smith | G349: Paper 2 Section A | H349: All tiers | I349: Common | J349: Open source
A350: ☐ | B350: English Literature | C350: An Inspector Calls | D350: An Inspector Calls: characters | E350: Inspector Goole | G350: Paper 2 Section A | H350: All tiers | I350: Common | J350: Open source
A351: ☐ | B351: English Literature | C351: An Inspector Calls | D351: An Inspector Calls: characters | E351: Sheila | G351: Paper 2 Section A | H351: All tiers | I351: Common | J351: Open source
A352: ☐ | B352: English Literature | C352: An Inspector Calls | D352: An Inspector Calls: dramatic methods | E352: Analyse stage directions | G352: Paper 2 Section A | H352: All tiers | I352: Common | J352: Open source
... A436: ☐ | B436: English Literature | C436: Power and Conflict poetry | D436: War Photographer | E436: Moral responsibility and public indifference | G436: Paper 2 Section B | H436: All tiers | I436: Common | J436: Open source
A437: ☐ | B437: English Literature | C437: Unseen poetry | F437: Analyse one unseen poem and compare methods in a second unseen poem. | G437: Paper 2 Section C | H437: All tiers | I437: Common | J437: Open source
A438: ☐ | B438: Geography | C438: Challenges in the human environment | D438: Energy | E438: Causes and impacts of insecurity | G438: Paper 2 Section C | H438: All tiers | I438: option_required | J438: Open source
A439: ☐ | B439: Geography | C439: Challenges in the human environment | D439: Energy | E439: Fossil-fuel extraction and a local renewable scheme | G439: Paper 2 Section C | H439: All tiers | I439: option_required | J439: Open source
A440: ☐ | B440: Geography | C440: Challenges in the human environment | D440: Energy | E440: Global energy consumption and supply | G440: Paper 2 Section C | H440: All tiers | I440: option_required | J440: Open source
A441: ☐ | B441: Geography | C441: Challenges in the human environment | D441: Energy | E441: Renewable and non-renewable strategies | G441: Paper 2 Section C | H441: All tiers | I441: option_required | J441: Open source
A442: ☐ | B442: Geography | C442: Challenges in the human environment | D442: Food | E442: A large-scale agricultural scheme and a local sustainable scheme | G442: Paper 2 Section C | H442: All tiers | I442: option_required | J442: Open source
A443: ☐ | B443: Geography | C443: Challenges in the human environment | D443: Food | E443: Causes and impacts of insecurity | G443: Paper 2 Section C | H443: All tiers | I443: option_required | J443: Open source
A444: ☐ | B444: Geography | C444: Challenges in the human environment | D444: Food | E444: Global food surplus and deficit | G444: Paper 2 Section C | H444: All tiers | I444: option_required | J444: Open source
A445: ☐ | B445: Geography | C445: Challenges in the human environment | D445: Food | E445: Increasing supply | G445: Paper 2 Section C | H445: All tiers | I445: option_required | J445: Open source
A446: ☐ | B446: Geography | C446: Challenges in the human environment | D446: Resource management overview | E446: Global inequalities in consumption | G446: Paper 2 Section C | H446: All tiers | I446: Common | J446: Open source
A447: ☐ | B447: Geography | C447: Challenges in the human environment | D447: Resource management overview | E447: Resource security | G447: Paper 2 Section C | H447: All tiers | I447: Common | J447: Open source
A448: ☐ | B448: Geography | C448: Challenges in the human environment | D448: Resource management overview | E448: Sustainability and environmental impacts | G448: Paper 2 Section C | H448: All tiers | I448: Common | J448: Open source
A449: ☐ | B449: Geography | C449: Challenges in the human environment | D449: Resource management overview | E449: UK food | G449: Paper 2 Section C | H449: All tiers | I449: Common | J449: Open source
... A627: ☐ | B627: Mathematics | C627: Algebra | D627: Sequences | E627: Quadratic | G627: All papers | H627: All tiers | I627: Common | J627: Open source
A628: ☐ | B628: Mathematics | C628: Algebra | D628: Simultaneous equations | F628: Solve two linear equations and linear-quadratic simultaneous equations algebraically and graphically. | G628: All papers | H628: All tiers | I628: Common | J628: Open source
A629: ☐ | B629: Mathematics | C629: Geometry and measures | D629: Angles and polygons | E629: Angle facts | G629: All papers | H629: All tiers | I629: Common | J629: Open source
A630: ☐ | B630: Mathematics | C630: Geometry and measures | D630: Angles and polygons | E630: Parallel lines | G630: All papers | H630: All tiers | I630: Common | J630: Open source
A631: ☐ | B631: Mathematics | C631: Geometry and measures | D631: Angles and polygons | E631: Polygons and geometrical reasoning | G631: All papers | H631: All tiers | I631: Common | J631: Open source
A632: ☐ | B632: Mathematics | C632: Geometry and measures | D632: Circle geometry | E632: Circle properties | G632: All papers | H632: higher | I632: Common | J632: Open source
A633: ☐ | B633: Mathematics | C633: Geometry and measures | D633: Circle geometry | E633: Equations of circles | G633: All papers | H633: higher | I633: Common | J633: Open source
A634: ☐ | B634: Mathematics | C634: Geometry and measures | D634: Circle geometry | E634: Tangents and circle theorems | G634: All papers | H634: higher | I634: Common | J634: Open source
A635: ☐ | B635: Mathematics | C635: Geometry and measures | D635: Congruence and similarity | E635: Area and volume scale factors | G635: All papers | H635: All tiers | I635: Common | J635: Open source
...

Sheet Summary
A1: Curriculum coverage by subject
A2: Subject | B2: Exam board | C2: Specification | D2: Detailed topics | E2: Covered | F2: Remaining | G2: Completion
A3: Business | B3: Edexcel | C3: 1BS0 | D3: 59 | E3: =COUNTIFS(Checklist!$B$4:$B$713,A3,Checklist!$A$4:$A$713,"☑") -> 0 | F3: =D3-E3 -> 59 | G3: =IFERROR(E3/D3,0) -> 0
A4: Combined Science | B4: AQA | C4: 8464 | D4: 142 | E4: =COUNTIFS(Checklist!$B$4:$B$713,A4,Checklist!$A$4:$A$713,"☑") -> 0 | F4: =D4-E4 -> 142 | G4: =IFERROR(E4/D4,0) -> 0
A5: Design and Technology | B5: AQA | C5: 8552 | D5: 107 | E5: =COUNTIFS(Checklist!$B$4:$B$713,A5,Checklist!$A$4:$A$713,"☑") -> 0 | F5: =D5-E5 -> 107 | G5: =IFERROR(E5/D5,0) -> 0
A6: English Language | B6: AQA | C6: 8700 | D6: 17 | E6: =COUNTIFS(Checklist!$B$4:$B$713,A6,Checklist!$A$4:$A$713,"☑") -> 0 | F6: =D6-E6 -> 17 | G6: =IFERROR(E6/D6,0) -> 0
A7: English Literature | B7: AQA | C7: 8702 | D7: 109 | E7: =COUNTIFS(Checklist!$B$4:$B$713,A7,Checklist!$A$4:$A$713,"☑") -> 0 | F7: =D7-E7 -> 109 | G7: =IFERROR(E7/D7,0) -> 0
A8: Geography | B8: AQA | C8: 8035 | D8: 112 | E8: =COUNTIFS(Checklist!$B$4:$B$713,A8,Checklist!$A$4:$A$713,"☑") -> 0 | F8: =D8-E8 -> 112 | G8: =IFERROR(E8/D8,0) -> 0
A9: History | B9: Edexcel | C9: 1HI0 | D9: 57 | E9: =COUNTIFS(Checklist!$B$4:$B$713,A9,Checklist!$A$4:$A$713,"☑") -> 0 | F9: =D9-E9 -> 57 | G9: =IFERROR(E9/D9,0) -> 0
A10: Mathematics | B10: AQA | C10: 8300 | D10: 107 | E10: =COUNTIFS(Checklist!$B$4:$B$713,A10,Checklist!$A$4:$A$713,"☑") -> 0 | F10: =D10-E10 -> 107 | G10: =IFERROR(E10/D10,0) -> 0
A12: All subjects | D12: =SUM(D3:D10) -> 710 | E12: =SUM(E3:E10) -> 0 | F12: =SUM(F3:F10) -> 710 | G12: =IFERROR(E12/D12,0) -> 0
